wechat_api-0.1.1.dist-info/METADATA
wechat_api-0.1.1.dist-info/WHEEL
wechat_api/__init__.py
wechat_api/aispeech.py
wechat_api/base.py
wechat_api/channels.py
wechat_api/core.py
wechat_api/exceptions.py
wechat_api/game.py
wechat_api/mini.py
wechat_api/models/__init__.py
wechat_api/models/base.py
wechat_api/models/mini.py
wechat_api/models/pay.py
wechat_api/models/platform.py
wechat_api/models/request.py
wechat_api/models/state.py
wechat_api/offi.py
wechat_api/pay.py
wechat_api/platform.py
wechat_api/state.py
wechat_api/store.py
wechat_api/tools.py
wechat_api/work.py
wechat_api/xwei.py
wechat_api-0.1.1.dist-info/RECORD
