Metadata-Version: 2.1
Name: wechat-api
Version: 0.1.1
Summary: a python wechat api sdk
Author-Email: RyomaHan <ryomahan1996@gmail.com>, FuWang <2497744746@qq.com>
License: MIT
Requires-Python: >=3.10
Requires-Dist: httpx>=0.24.0
Requires-Dist: pydantic>=1.10.7
Requires-Dist: cryptography>=40.0.2
